dj_palette-0.0.2.1.dist-info/licenses/LICENSE
migrations/0001_initial.py
migrations/__init__.py
migrations/__pycache__/0001_initial.cpython-313.pyc
migrations/__pycache__/__init__.cpython-313.pyc
templatetags/__init__.py
templatetags/admin_back.py
templatetags/palette.py
templatetags/__pycache__/__init__.cpython-313.pyc
templatetags/__pycache__/admin_back.cpython-313.pyc
templatetags/__pycache__/custom_admin_tags.cpython-313.pyc
templatetags/__pycache__/palette.cpython-313.pyc
dj_palette-0.0.2.1.dist-info/METADATA
dj_palette-0.0.2.1.dist-info/WHEEL
dj_palette-0.0.2.1.dist-info/top_level.txt
dj_palette-0.0.2.1.dist-info/RECORD
